llamalib/__init__.py
llamalib-0.0.1.dist-info/licenses/LICENSE
llamalib-0.0.1.dist-info/METADATA
llamalib-0.0.1.dist-info/WHEEL
llamalib-0.0.1.dist-info/top_level.txt
llamalib-0.0.1.dist-info/RECORD
